tap_stackerhq/__init__.py
tap_stackerhq/client.py
tap_stackerhq/schemas/assets.json
tap_stackerhq/schemas/damages.json
tap_stackerhq/schemas/fines.json
tap_stackerhq/schemas/investigations.json
tap_stackerhq/schemas/investigations_regions.json
tap_stackerhq/schemas/regions.json
tap_stackerhq/schemas/rentals.json
tap_stackerhq/streams.py
tap_stackerhq/tap.py
tap_stackerhq-0.0.9.dist-info/LICENSE
tap_stackerhq-0.0.9.dist-info/METADATA
tap_stackerhq-0.0.9.dist-info/WHEEL
tap_stackerhq-0.0.9.dist-info/entry_points.txt
tap_stackerhq-0.0.9.dist-info/RECORD
